CHANGES.rst
LICENSE
MANIFEST.in
README.rst
setup.py
docs/Makefile
docs/conf.py
docs/index.rst
docs/index.rst.orig
docs/make.bat
simpleubjson/__init__.py
simpleubjson/compat.py
simpleubjson/draft8.py
simpleubjson/draft9.py
simpleubjson/exceptions.py
simpleubjson/version.py
simpleubjson.egg-info/PKG-INFO
simpleubjson.egg-info/SOURCES.txt
simpleubjson.egg-info/dependency_links.txt
simpleubjson.egg-info/top_level.txt
simpleubjson.egg-info/zip-safe
simpleubjson/tests/__init__.py
simpleubjson/tests/test_ubjson.py
simpleubjson/tests/test_ubjson_d9.py
simpleubjson/tests/data/CouchDB4k.compact.json
simpleubjson/tests/data/CouchDB4k.formatted.json
simpleubjson/tests/data/MediaContent.compact.json
simpleubjson/tests/data/MediaContent.formatted.json
simpleubjson/tests/data/TwitterTimeline.compact.json
simpleubjson/tests/data/TwitterTimeline.formatted.json
simpleubjson/tools/__init__.py
simpleubjson/tools/benchmark.py
simpleubjson/tools/inspect.py