Metadata-Version: 1.1
Name: simpleubjson
Version: 0.7.0
Summary: Simple universal binary json decoder/encoder for Python.
Home-page: http://code.google.com/p/simpleubjson/
Author: Alexander Shorin
Author-email: kxepal@gmail.com
License: BSD
Platform: UNKNOWN
Classifier: Development Status :: 4 - Beta
Classifier: Intended Audience :: Developers
Classifier: License :: OSI Approved :: BSD License
Classifier: Operating System :: OS Independent
Classifier: Programming Language :: Python
Classifier: Topic :: Software Development :: Libraries :: Python Modules
